{
	"name": "dssourceforEach",
	"properties": {
		"linkedServiceName": {
			"referenceName": "AzureSqlDatabase1",
			"type": "LinkedServiceReference"
		},
		"parameters": {
			"tablename": {
				"type": "string"
			},
			"tableschema": {
				"type": "string"
			}
		},
		"annotations": [],
		"type": "AzureSqlTable",
		"schema": [],
		"typeProperties": {
			"schema": {
				"value": "@dataset().tableschema",
				"type": "Expression"
			},
			"table": {
				"value": "@dataset().tablename",
				"type": "Expression"
			}
		}
	},
	"type": "Microsoft.DataFactory/factories/datasets"
}